entry.py
setup.py
vidtag.py
vidtag-0.1.8.dist-info/entry_points.txt
vidtag-0.1.8.dist-info/WHEEL
vidtag-0.1.8.dist-info/METADATA
vidtag-0.1.8.dist-info/RECORD
