Metadata-Version: 2.1
Name: vidtag
Version: 0.1.8
Summary: 
Author: Oskar
Author-email: oskar.alund@gmail.com
Requires-Python: >=3.0,<4.0
Classifier: Programming Language :: Python :: 3
Classifier: Programming Language :: Python :: 3.4
Classifier: Programming Language :: Python :: 3.5
Classifier: Programming Language :: Python :: 3.6
Classifier: Programming Language :: Python :: 3.7
Requires-Dist: numpy (>=1.16,<2.0)
Requires-Dist: opencv-python (>=4.1,<5.0)
Requires-Dist: tensorflow (>=2.0,<3.0)
Requires-Dist: tqdm (>=4.40,<5.0)
